LICENSE.txt
MANIFEST.in
README.md
requirements.txt
setup.py
airsensor/__init__.py
airsensor/core.py
airsensor_py.egg-info/PKG-INFO
airsensor_py.egg-info/SOURCES.txt
airsensor_py.egg-info/dependency_links.txt
airsensor_py.egg-info/top_level.txt
bin/airsensor-py