Metadata-Version: 1.0
Name: airsensor-py
Version: 0.0.6
Summary: Python package for getting sensor values from an Ambient Air Sensor
Home-page: https://github.com/dfederschmidt/airsensor-py
Author: Daniel Federschmidt
Author-email: daniel@federschmidt.xyz
License: UNKNOWN
Platform: UNKNOWN
